leaf_server_common/__init__.py
leaf_server_common/logging/README.md
leaf_server_common/logging/__init__.py
leaf_server_common/logging/logging_setup.py
leaf_server_common/logging/message_types.py
leaf_server_common/logging/open_telemetry_logging_handler.py
leaf_server_common/logging/request_logger_adapter.py
leaf_server_common/logging/service_log_record.py
leaf_server_common/logging/structured_log_record.py
leaf_server_common/server/__init__.py
leaf_server_common/server/atomic_counter.py
leaf_server_common/server/grpc_metadata_forwarder.py
leaf_server_common/server/probe.py
leaf_server_common/server/request_logger.py
leaf_server_common/server/server_lifetime.py
leaf_server_common/server/server_loop_callbacks.py
leaf_server_common/server/service_info.py
leaf_server_common-0.1.23.dist-info/licenses/LICENSE.txt
leaf_server_common-0.1.23.dist-info/METADATA
leaf_server_common-0.1.23.dist-info/WHEEL
leaf_server_common-0.1.23.dist-info/top_level.txt
leaf_server_common-0.1.23.dist-info/RECORD
