Metadata-Version: 2.4
Name: leaf-server-common
Version: 0.1.23
Summary: Library for common service infrastructure for use by Cognizant AI Lab services
Author-email: Dan Fink <Daniel.Fink@cognizant.com>
License-Expression: Apache-2.0
Project-URL: Homepage, https://github.com/cognizant-ai-lab/leaf-server-common
Project-URL: Repository, https://github.com/cognizant-ai-lab/leaf-server-common
Project-URL: Documentation, https://github.com/cognizant-ai-lab/leaf-server-common#readme
Keywords: service,infrastructure,grpc
Classifier: Programming Language :: Python :: 3
Classifier: Operating System :: OS Independent
Classifier: Development Status :: 5 - Production/Stable
Classifier: Intended Audience :: Developers
Requires-Python: >=3.10
License-File: LICENSE.txt
Requires-Dist: leaf-common>=1.2.31
Requires-Dist: grpcio>=1.62.0
Requires-Dist: grpcio-health-checking>=1.62.0
Requires-Dist: grpcio-reflection>=1.62.0
Requires-Dist: grpcio-tools>=1.62.0
Requires-Dist: opentelemetry-api>=1.39.0
Requires-Dist: opentelemetry-sdk>=1.39.0
Requires-Dist: opentelemetry-exporter-otlp>=1.39.0
Dynamic: license-file
